surfgram_internal-0.2.dist-info/METADATA
surfgram_internal-0.2.dist-info/WHEEL
surfgram_internal-0.2.dist-info/licenses/LICENSE
surfgram_internal/__init__.py
surfgram_internal/surfgram_internal.cp312-win_amd64.pyd
surfgram_internal-0.2.dist-info/RECORD
