Metadata-Version: 2.4
Name: surfgram-internal
Version: 0.2
Classifier: Development Status :: 2 - Pre-Alpha
Classifier: Intended Audience :: Developers
Classifier: License :: OSI Approved :: MIT License
Classifier: License :: OSI Approved :: Apache Software License
Classifier: Programming Language :: Python :: 3
Classifier: Programming Language :: Python :: 3.8
Classifier: Programming Language :: Python :: 3.9
Classifier: Programming Language :: Python :: 3.10
Classifier: Programming Language :: Python :: 3.11
Classifier: Programming Language :: Python :: 3.12
Classifier: Programming Language :: Rust
Classifier: Topic :: Software Development :: Libraries :: Python Modules
License-File: LICENSE
Summary: Internal utilities for Surfgram. Not for external use.
Keywords: surfgram,internal,utils
Author-email: anybody <help.surfgram@gmail.com>
License: MIT
Requires-Python: >=3.8
Project-URL: Homepage, https://github.com/surfgram/surfgram-internal
Project-URL: Repository, https://github.com/surfgram/surfgram-internal.git
Project-URL: Issues, https://github.com/surfgram/surfgram-internal/issues
